bravocapital/__init__.py
bravocapital-1.0.11.dist-info/DESCRIPTION.rst
bravocapital-1.0.11.dist-info/METADATA
bravocapital-1.0.11.dist-info/RECORD
bravocapital-1.0.11.dist-info/WHEEL
bravocapital-1.0.11.dist-info/metadata.json
bravocapital-1.0.11.dist-info/top_level.txt
