Metadata-Version: 2.0
Name: bravocapital
Version: 1.0.11
Summary: Python package for Bravo Capital!
Home-page: https://github.com/manoelgadi/bravocapital/bravocapital
Author: Manoel Gadi
Author-email: manoel.gadi@bravocapital.es
License: MIT
Platform: UNKNOWN
